<annotationInfo>
<item  id="27" filename="KWTAmini8_0/top.cc" linenumber="122" name="tmp" contextFuncName="KWTA_mini8_theta" moduleName="KWTA_mini8_theta" rtlName="tmp_fu_878_p2" latency="0" BRAM="-1" DSP="-1" FF="0" LUT="11" fileDirectory="/home/tingyuan/Temporary/vivado-outputs"><\/item>
<item  id="31" filename="KWTAmini8_0/top.cc" linenumber="167" name="tmp_3" contextFuncName="KWTA_mini8_theta" moduleName="KWTA_mini8_theta" rtlName="tmp_3_fu_887_p2" latency="0" BRAM="-1" DSP="-1" FF="0" LUT="11" fileDirectory="/home/tingyuan/Temporary/vivado-outputs"><\/item>
<item  id="40" filename="KWTAmini8_0/top.cc" linenumber="170" name="p_Result_6" contextFuncName="KWTA_mini8_theta" moduleName="KWTA_mini8_theta" rtlName="p_Result_6_reg_1488" latency="0" BRAM="-1" DSP="-1" FF="-1" LUT="-1" fileDirectory="/home/tingyuan/Temporary/vivado-outputs"><\/item>
<item  id="41" filename="KWTAmini8_0/top.cc" linenumber="171" name="p_Result_7" contextFuncName="KWTA_mini8_theta" moduleName="KWTA_mini8_theta" rtlName="p_Result_7_reg_1493" latency="0" BRAM="-1" DSP="-1" FF="-1" LUT="-1" fileDirectory="/home/tingyuan/Temporary/vivado-outputs"><\/item>
<item  id="42" filename="KWTAmini8_0/top.cc" linenumber="172" name="tmp_offset_V" contextFuncName="KWTA_mini8_theta" moduleName="KWTA_mini8_theta" rtlName="tmp_offset_V_fu_910_p4" latency="0" BRAM="-1" DSP="-1" FF="-1" LUT="-1" fileDirectory="/home/tingyuan/Temporary/vivado-outputs"><\/item>
<item  id="43" filename="KWTAmini8_0/top.cc" linenumber="173" name="tmp_8" contextFuncName="KWTA_mini8_theta" moduleName="KWTA_mini8_theta" rtlName="tmp_8_fu_919_p1" latency="0" BRAM="-1" DSP="-1" FF="-1" LUT="-1" fileDirectory="/home/tingyuan/Temporary/vivado-outputs"><\/item>
<item  id="46" filename="KWTAmini8_0/top.cc" linenumber="173" name="tmp_33" contextFuncName="KWTA_mini8_theta" moduleName="KWTA_mini8_theta" rtlName="tmp_33_fu_970_p1" latency="0" BRAM="-1" DSP="-1" FF="-1" LUT="-1" fileDirectory="/home/tingyuan/Temporary/vivado-outputs"><\/item>
<item  id="47" filename="KWTAmini8_0/top.cc" linenumber="174" name="tmp_s" contextFuncName="KWTA_mini8_theta" moduleName="KWTA_mini8_theta" rtlName="tmp_s_fu_974_p2" latency="0" BRAM="-1" DSP="-1" FF="0" LUT="11" fileDirectory="/home/tingyuan/Temporary/vivado-outputs"><\/item>
<item  id="50" filename="KWTAmini8_0/top.cc" linenumber="173" name="loc_V_2_trunc" contextFuncName="KWTA_mini8_theta" moduleName="KWTA_mini8_theta" rtlName="loc_V_2_trunc_fu_980_p2" latency="0" BRAM="-1" DSP="-1" FF="0" LUT="15" fileDirectory="/home/tingyuan/Temporary/vivado-outputs"><\/item>
<item  id="51" filename="KWTAmini8_0/top.cc" linenumber="181" name="p_Result_2" contextFuncName="KWTA_mini8_theta" moduleName="KWTA_mini8_theta" rtlName="p_Result_2_fu_986_p5" latency="0" BRAM="-1" DSP="-1" FF="-1" LUT="-1" fileDirectory="/home/tingyuan/Temporary/vivado-outputs"><\/item>
<item  id="54" filename="KWTAmini8_0/top.cc" linenumber="176" name="tmp_13" contextFuncName="KWTA_mini8_theta" moduleName="KWTA_mini8_theta" rtlName="tmp_13_fu_998_p1" latency="0" BRAM="-1" DSP="-1" FF="-1" LUT="-1" fileDirectory="/home/tingyuan/Temporary/vivado-outputs"><\/item>
<item  id="55" filename="KWTAmini8_0/top.cc" linenumber="176" name="i_assign" contextFuncName="KWTA_mini8_theta" moduleName="KWTA_mini8_theta" rtlName="i_assign_fu_1020_p1" latency="0" BRAM="-1" DSP="-1" FF="-1" LUT="-1" fileDirectory="/home/tingyuan/Temporary/vivado-outputs"><\/item>
<item  id="58" filename="KWTAmini8_0/top.cc" linenumber="176" name="p_Result_s_36" contextFuncName="KWTA_mini8_theta" moduleName="KWTA_mini8_theta" rtlName="p_Result_s_36_fu_1023_p4" latency="0" BRAM="-1" DSP="-1" FF="-1" LUT="-1" fileDirectory="/home/tingyuan/Temporary/vivado-outputs"><\/item>
<item  id="61" filename="KWTAmini8_0/top.cc" linenumber="177" name="i_assign_1" contextFuncName="KWTA_mini8_theta" moduleName="KWTA_mini8_theta" rtlName="i_assign_1_fu_1002_p1" latency="0" BRAM="-1" DSP="-1" FF="-1" LUT="-1" fileDirectory="/home/tingyuan/Temporary/vivado-outputs"><\/item>
<item  id="62" filename="KWTAmini8_0/top.cc" linenumber="177" name="p_Result_1" contextFuncName="KWTA_mini8_theta" moduleName="KWTA_mini8_theta" rtlName="p_Result_1_fu_1005_p4" latency="0" BRAM="-1" DSP="-1" FF="-1" LUT="-1" fileDirectory="/home/tingyuan/Temporary/vivado-outputs"><\/item>
<item  id="75" filename="KWTAmini8_0/top.cc" linenumber="126" name="tmp_1" contextFuncName="KWTA_mini8_theta" moduleName="KWTA_mini8_theta" rtlName="tmp_1_fu_924_p2" latency="0" BRAM="-1" DSP="-1" FF="0" LUT="29" fileDirectory="/home/tingyuan/Temporary/vivado-outputs"><\/item>
<item  id="76" filename="KWTAmini8_0/top.cc" linenumber="126" name="tmp_10" contextFuncName="KWTA_mini8_theta" moduleName="KWTA_mini8_theta" rtlName="tmp_10_fu_930_p3" latency="0" BRAM="-1" DSP="-1" FF="-1" LUT="-1" fileDirectory="/home/tingyuan/Temporary/vivado-outputs"><\/item>
<item  id="77" filename="KWTAmini8_0/top.cc" linenumber="126" name="or_cond" contextFuncName="KWTA_mini8_theta" moduleName="KWTA_mini8_theta" rtlName="or_cond_fu_937_p2" latency="0" BRAM="-1" DSP="-1" FF="0" LUT="2" fileDirectory="/home/tingyuan/Temporary/vivado-outputs"><\/item>
<item  id="81" filename="KWTAmini8_0/top.cc" linenumber="131" name="tmp_32" contextFuncName="KWTA_mini8_theta" moduleName="KWTA_mini8_theta" rtlName="tmp_32_reg_1518" latency="0" BRAM="-1" DSP="-1" FF="-1" LUT="-1" fileDirectory="/home/tingyuan/Temporary/vivado-outputs"><\/item>
<item  id="87" filename="KWTAmini8_0/top.cc" linenumber="135" name="tmp_5" contextFuncName="KWTA_mini8_theta" moduleName="KWTA_mini8_theta" rtlName="tmp_5_fu_959_p1" latency="0" BRAM="-1" DSP="-1" FF="-1" LUT="-1" fileDirectory="/home/tingyuan/Temporary/vivado-outputs"><\/item>
<item  id="90" filename="KWTAmini8_0/top.cc" linenumber="137" name="tmp_6" contextFuncName="KWTA_mini8_theta" moduleName="KWTA_mini8_theta" rtlName="tmp_6_fu_1034_p2" latency="0" BRAM="-1" DSP="-1" FF="0" LUT="27" fileDirectory="/home/tingyuan/Temporary/vivado-outputs"><\/item>
<item  id="92" filename="KWTAmini8_0/top.cc" linenumber="138" name="tmp_7" contextFuncName="KWTA_mini8_theta" moduleName="KWTA_mini8_theta" rtlName="tmp_7_fu_1045_p1" latency="0" BRAM="-1" DSP="-1" FF="-1" LUT="-1" fileDirectory="/home/tingyuan/Temporary/vivado-outputs"><\/item>
<item  id="95" filename="KWTAmini8_0/top.cc" linenumber="138" name="p_Result_s" contextFuncName="KWTA_mini8_theta" moduleName="KWTA_mini8_theta" rtlName="p_Result_s_fu_1049_p4" latency="0" BRAM="-1" DSP="-1" FF="-1" LUT="-1" fileDirectory="/home/tingyuan/Temporary/vivado-outputs"><\/item>
<item  id="96" filename="KWTAmini8_0/top.cc" linenumber="139" name="tmp_11" contextFuncName="KWTA_mini8_theta" moduleName="KWTA_mini8_theta" rtlName="tmp_11_fu_1059_p2" latency="0" BRAM="-1" DSP="-1" FF="0" LUT="11" fileDirectory="/home/tingyuan/Temporary/vivado-outputs"><\/item>
<item  id="99" filename="KWTAmini8_0/top.cc" linenumber="138" name="loc_V_trunc" contextFuncName="KWTA_mini8_theta" moduleName="KWTA_mini8_theta" rtlName="loc_V_trunc_fu_1065_p2" latency="0" BRAM="-1" DSP="-1" FF="0" LUT="15" fileDirectory="/home/tingyuan/Temporary/vivado-outputs"><\/item>
<item  id="100" filename="KWTAmini8_0/top.cc" linenumber="150" name="p_Result_4" contextFuncName="KWTA_mini8_theta" moduleName="KWTA_mini8_theta" rtlName="p_Result_4_fu_1071_p5" latency="0" BRAM="-1" DSP="-1" FF="-1" LUT="-1" fileDirectory="/home/tingyuan/Temporary/vivado-outputs"><\/item>
<item  id="106" filename="KWTAmini8_0/top.cc" linenumber="142" name="tmp_15" contextFuncName="KWTA_mini8_theta" moduleName="KWTA_mini8_theta" rtlName="tmp_15_fu_1088_p1" latency="0" BRAM="-1" DSP="-1" FF="-1" LUT="-1" fileDirectory="/home/tingyuan/Temporary/vivado-outputs"><\/item>
<item  id="108" filename="KWTAmini8_0/top.cc" linenumber="142" name="i_assign_2" contextFuncName="KWTA_mini8_theta" moduleName="KWTA_mini8_theta" rtlName="i_assign_2_fu_1103_p1" latency="0" BRAM="-1" DSP="-1" FF="-1" LUT="-1" fileDirectory="/home/tingyuan/Temporary/vivado-outputs"><\/item>
<item  id="111" filename="KWTAmini8_0/top.cc" linenumber="142" name="p_Result_3" contextFuncName="KWTA_mini8_theta" moduleName="KWTA_mini8_theta" rtlName="p_Result_3_fu_1107_p4" latency="0" BRAM="-1" DSP="-1" FF="-1" LUT="-1" fileDirectory="/home/tingyuan/Temporary/vivado-outputs"><\/item>
<item  id="115" filename="KWTAmini8_0/top.cc" linenumber="144" name="tmp_16" contextFuncName="KWTA_mini8_theta" moduleName="KWTA_mini8_theta" rtlName="tmp_16_fu_1118_p2" latency="0" BRAM="-1" DSP="-1" FF="0" LUT="29" fileDirectory="/home/tingyuan/Temporary/vivado-outputs"><\/item>
<item  id="118" filename="KWTAmini8_0/top.cc" linenumber="147" name="i_assign_3" contextFuncName="KWTA_mini8_theta" moduleName="KWTA_mini8_theta" rtlName="i_assign_3_fu_1124_p1" latency="0" BRAM="-1" DSP="-1" FF="-1" LUT="-1" fileDirectory="/home/tingyuan/Temporary/vivado-outputs"><\/item>
<item  id="119" filename="KWTAmini8_0/top.cc" linenumber="147" name="p_Result_5" contextFuncName="KWTA_mini8_theta" moduleName="KWTA_mini8_theta" rtlName="p_Result_5_fu_1127_p4" latency="0" BRAM="-1" DSP="-1" FF="-1" LUT="-1" fileDirectory="/home/tingyuan/Temporary/vivado-outputs"><\/item>
<item  id="127" filename="KWTAmini8_0/top.cc" linenumber="154" name="p_not" contextFuncName="KWTA_mini8_theta" moduleName="KWTA_mini8_theta" rtlName="p_not_fu_964_p2" latency="0" BRAM="-1" DSP="-1" FF="0" LUT="71" fileDirectory="/home/tingyuan/Temporary/vivado-outputs"><\/item>
<item  id="128" filename="KWTAmini8_0/top.cc" linenumber="154" name="p_Val2_2" contextFuncName="KWTA_mini8_theta" moduleName="KWTA_mini8_theta" rtlName="p_Val2_2_fu_1142_p2" latency="0" BRAM="-1" DSP="-1" FF="0" LUT="64" fileDirectory="/home/tingyuan/Temporary/vivado-outputs"><\/item>
<item  id="129" filename="KWTAmini8_0/top.cc" linenumber="90" name="AA_V" contextFuncName="log_2_64bit" moduleName="KWTA_mini8_theta" rtlName="AA_V_fu_1146_p1" latency="0" BRAM="-1" DSP="-1" FF="-1" LUT="-1" fileDirectory="/home/tingyuan/Temporary/vivado-outputs"><\/item>
<item  id="130" filename="KWTAmini8_0/top.cc" linenumber="90" name="BB_V" contextFuncName="log_2_64bit" moduleName="KWTA_mini8_theta" rtlName="BB_V_fu_1150_p4" latency="0" BRAM="-1" DSP="-1" FF="-1" LUT="-1" fileDirectory="/home/tingyuan/Temporary/vivado-outputs"><\/item>
<item  id="131" filename="KWTAmini8_0/top.cc" linenumber="90" name="CC_V" contextFuncName="log_2_64bit" moduleName="KWTA_mini8_theta" rtlName="CC_V_fu_1160_p4" latency="0" BRAM="-1" DSP="-1" FF="-1" LUT="-1" fileDirectory="/home/tingyuan/Temporary/vivado-outputs"><\/item>
<item  id="132" filename="KWTAmini8_0/top.cc" linenumber="90" name="DD_V" contextFuncName="log_2_64bit" moduleName="KWTA_mini8_theta" rtlName="DD_V_fu_1170_p4" latency="0" BRAM="-1" DSP="-1" FF="-1" LUT="-1" fileDirectory="/home/tingyuan/Temporary/vivado-outputs"><\/item>
<item  id="133" filename="KWTAmini8_0/top.cc" linenumber="91" name="tmp_12" contextFuncName="log_2_64bit" moduleName="KWTA_mini8_theta" rtlName="tmp_12_fu_1180_p2" latency="0" BRAM="-1" DSP="-1" FF="0" LUT="13" fileDirectory="/home/tingyuan/Temporary/vivado-outputs"><\/item>
<item  id="169" filename="KWTAmini8_0/top.cc" linenumber="92" name="p_0167_0_i1_cast" contextFuncName="log_2_64bit" moduleName="KWTA_mini8_theta" rtlName="p_0167_0_i1_cast_fu_1186_p1" latency="0" BRAM="-1" DSP="-1" FF="-1" LUT="-1" fileDirectory="/home/tingyuan/Temporary/vivado-outputs"><\/item>
<item  id="170" filename="KWTAmini8_0/top.cc" linenumber="92" name="tmp_19" contextFuncName="log_2_64bit" moduleName="KWTA_mini8_theta" rtlName="tmp_19_fu_1190_p2" latency="0" BRAM="-1" DSP="-1" FF="0" LUT="13" fileDirectory="/home/tingyuan/Temporary/vivado-outputs"><\/item>
<item  id="206" filename="KWTAmini8_0/top.cc" linenumber="93" name="p_0252_0_i1_cast" contextFuncName="log_2_64bit" moduleName="KWTA_mini8_theta" rtlName="p_0252_0_i1_cast_fu_1196_p1" latency="0" BRAM="-1" DSP="-1" FF="-1" LUT="-1" fileDirectory="/home/tingyuan/Temporary/vivado-outputs"><\/item>
<item  id="207" filename="KWTAmini8_0/top.cc" linenumber="93" name="tmp_20" contextFuncName="log_2_64bit" moduleName="KWTA_mini8_theta" rtlName="tmp_20_fu_1200_p2" latency="0" BRAM="-1" DSP="-1" FF="0" LUT="13" fileDirectory="/home/tingyuan/Temporary/vivado-outputs"><\/item>
<item  id="243" filename="KWTAmini8_0/top.cc" linenumber="94" name="tmp_21" contextFuncName="log_2_64bit" moduleName="KWTA_mini8_theta" rtlName="tmp_21_fu_1206_p2" latency="0" BRAM="-1" DSP="-1" FF="0" LUT="13" fileDirectory="/home/tingyuan/Temporary/vivado-outputs"><\/item>
<item  id="279" filename="KWTAmini8_0/top.cc" linenumber="95" name="p_0244_0_i1_cast8" contextFuncName="log_2_64bit" moduleName="KWTA_mini8_theta" rtlName="p_0244_0_i1_cast8_fu_1212_p1" latency="0" BRAM="-1" DSP="-1" FF="-1" LUT="-1" fileDirectory="/home/tingyuan/Temporary/vivado-outputs"><\/item>
<item  id="280" filename="KWTAmini8_0/top.cc" linenumber="95" name="p_0244_0_i1_cast" contextFuncName="log_2_64bit" moduleName="KWTA_mini8_theta" rtlName="p_0244_0_i1_cast_fu_1216_p1" latency="0" BRAM="-1" DSP="-1" FF="-1" LUT="-1" fileDirectory="/home/tingyuan/Temporary/vivado-outputs"><\/item>
<item  id="281" filename="KWTAmini8_0/top.cc" linenumber="95" name="tmp2" contextFuncName="log_2_64bit" moduleName="KWTA_mini8_theta" rtlName="tmp2_fu_1220_p2" latency="0" BRAM="-1" DSP="-1" FF="0" LUT="15" fileDirectory="/home/tingyuan/Temporary/vivado-outputs"><\/item>
<item  id="282" filename="KWTAmini8_0/top.cc" linenumber="95" name="tmp2_cast" contextFuncName="log_2_64bit" moduleName="KWTA_mini8_theta" rtlName="tmp2_cast_fu_1225_p1" latency="0" BRAM="-1" DSP="-1" FF="-1" LUT="-1" fileDirectory="/home/tingyuan/Temporary/vivado-outputs"><\/item>
<item  id="283" filename="KWTAmini8_0/top.cc" linenumber="95" name="tmp3" contextFuncName="log_2_64bit" moduleName="KWTA_mini8_theta" rtlName="tmp3_fu_1229_p2" latency="0" BRAM="-1" DSP="-1" FF="0" LUT="15" fileDirectory="/home/tingyuan/Temporary/vivado-outputs"><\/item>
<item  id="284" filename="KWTAmini8_0/top.cc" linenumber="95" name="tmp3_cast" contextFuncName="log_2_64bit" moduleName="KWTA_mini8_theta" rtlName="tmp3_cast_fu_1234_p1" latency="0" BRAM="-1" DSP="-1" FF="-1" LUT="-1" fileDirectory="/home/tingyuan/Temporary/vivado-outputs"><\/item>
<item  id="285" filename="KWTAmini8_0/top.cc" linenumber="95" name="loc1_V" contextFuncName="log_2_64bit" moduleName="KWTA_mini8_theta" rtlName="loc1_V_fu_1238_p2" latency="0" BRAM="-1" DSP="-1" FF="0" LUT="15" fileDirectory="/home/tingyuan/Temporary/vivado-outputs"><\/item>
<item  id="287" filename="KWTAmini8_0/top.cc" linenumber="155" name="tmp_22" contextFuncName="KWTA_mini8_theta" moduleName="KWTA_mini8_theta" rtlName="tmp_22_fu_1250_p1" latency="0" BRAM="-1" DSP="-1" FF="-1" LUT="-1" fileDirectory="/home/tingyuan/Temporary/vivado-outputs"><\/item>
<item  id="290" filename="KWTAmini8_0/top.cc" linenumber="155" name="p_not1" contextFuncName="KWTA_mini8_theta" moduleName="KWTA_mini8_theta" rtlName="p_not1_fu_1255_p2" latency="0" BRAM="-1" DSP="-1" FF="0" LUT="71" fileDirectory="/home/tingyuan/Temporary/vivado-outputs"><\/item>
<item  id="291" filename="KWTAmini8_0/top.cc" linenumber="155" name="p_Val2_7" contextFuncName="KWTA_mini8_theta" moduleName="KWTA_mini8_theta" rtlName="p_Val2_7_fu_1261_p2" latency="0" BRAM="-1" DSP="-1" FF="0" LUT="64" fileDirectory="/home/tingyuan/Temporary/vivado-outputs"><\/item>
<item  id="292" filename="KWTAmini8_0/top.cc" linenumber="90" name="AA_V_1" contextFuncName="log_2_64bit" moduleName="KWTA_mini8_theta" rtlName="AA_V_1_fu_1267_p1" latency="0" BRAM="-1" DSP="-1" FF="-1" LUT="-1" fileDirectory="/home/tingyuan/Temporary/vivado-outputs"><\/item>
<item  id="293" filename="KWTAmini8_0/top.cc" linenumber="90" name="BB_V_1" contextFuncName="log_2_64bit" moduleName="KWTA_mini8_theta" rtlName="BB_V_1_reg_1631" latency="0" BRAM="-1" DSP="-1" FF="-1" LUT="-1" fileDirectory="/home/tingyuan/Temporary/vivado-outputs"><\/item>
<item  id="294" filename="KWTAmini8_0/top.cc" linenumber="90" name="CC_V_1" contextFuncName="log_2_64bit" moduleName="KWTA_mini8_theta" rtlName="CC_V_1_reg_1636" latency="0" BRAM="-1" DSP="-1" FF="-1" LUT="-1" fileDirectory="/home/tingyuan/Temporary/vivado-outputs"><\/item>
<item  id="295" filename="KWTAmini8_0/top.cc" linenumber="90" name="DD_V_1" contextFuncName="log_2_64bit" moduleName="KWTA_mini8_theta" rtlName="DD_V_1_reg_1641" latency="0" BRAM="-1" DSP="-1" FF="-1" LUT="-1" fileDirectory="/home/tingyuan/Temporary/vivado-outputs"><\/item>
<item  id="296" filename="KWTAmini8_0/top.cc" linenumber="91" name="tmp_23" contextFuncName="log_2_64bit" moduleName="KWTA_mini8_theta" rtlName="tmp_23_fu_1301_p2" latency="0" BRAM="-1" DSP="-1" FF="0" LUT="13" fileDirectory="/home/tingyuan/Temporary/vivado-outputs"><\/item>
<item  id="332" filename="KWTAmini8_0/top.cc" linenumber="92" name="p_0167_0_i_cast" contextFuncName="log_2_64bit" moduleName="KWTA_mini8_theta" rtlName="p_0167_0_i_cast_fu_1306_p1" latency="0" BRAM="-1" DSP="-1" FF="-1" LUT="-1" fileDirectory="/home/tingyuan/Temporary/vivado-outputs"><\/item>
<item  id="333" filename="KWTAmini8_0/top.cc" linenumber="92" name="tmp_24" contextFuncName="log_2_64bit" moduleName="KWTA_mini8_theta" rtlName="tmp_24_fu_1310_p2" latency="0" BRAM="-1" DSP="-1" FF="0" LUT="13" fileDirectory="/home/tingyuan/Temporary/vivado-outputs"><\/item>
<item  id="369" filename="KWTAmini8_0/top.cc" linenumber="93" name="p_0252_0_i_cast" contextFuncName="log_2_64bit" moduleName="KWTA_mini8_theta" rtlName="p_0252_0_i_cast_fu_1315_p1" latency="0" BRAM="-1" DSP="-1" FF="-1" LUT="-1" fileDirectory="/home/tingyuan/Temporary/vivado-outputs"><\/item>
<item  id="370" filename="KWTAmini8_0/top.cc" linenumber="93" name="tmp_25" contextFuncName="log_2_64bit" moduleName="KWTA_mini8_theta" rtlName="tmp_25_fu_1319_p2" latency="0" BRAM="-1" DSP="-1" FF="0" LUT="13" fileDirectory="/home/tingyuan/Temporary/vivado-outputs"><\/item>
<item  id="406" filename="KWTAmini8_0/top.cc" linenumber="94" name="p_0248_0_i_cast" contextFuncName="log_2_64bit" moduleName="KWTA_mini8_theta" rtlName="p_0248_0_i_cast_fu_1324_p1" latency="0" BRAM="-1" DSP="-1" FF="-1" LUT="-1" fileDirectory="/home/tingyuan/Temporary/vivado-outputs"><\/item>
<item  id="407" filename="KWTAmini8_0/top.cc" linenumber="94" name="tmp_26" contextFuncName="log_2_64bit" moduleName="KWTA_mini8_theta" rtlName="tmp_26_fu_1328_p2" latency="0" BRAM="-1" DSP="-1" FF="0" LUT="13" fileDirectory="/home/tingyuan/Temporary/vivado-outputs"><\/item>
<item  id="443" filename="KWTAmini8_0/top.cc" linenumber="95" name="p_0244_0_i_cast7" contextFuncName="log_2_64bit" moduleName="KWTA_mini8_theta" rtlName="p_0244_0_i_cast7_fu_1333_p1" latency="0" BRAM="-1" DSP="-1" FF="-1" LUT="-1" fileDirectory="/home/tingyuan/Temporary/vivado-outputs"><\/item>
<item  id="444" filename="KWTAmini8_0/top.cc" linenumber="95" name="p_0244_0_i_cast" contextFuncName="log_2_64bit" moduleName="KWTA_mini8_theta" rtlName="p_0244_0_i_cast_fu_1337_p1" latency="0" BRAM="-1" DSP="-1" FF="-1" LUT="-1" fileDirectory="/home/tingyuan/Temporary/vivado-outputs"><\/item>
<item  id="445" filename="KWTAmini8_0/top.cc" linenumber="95" name="tmp5" contextFuncName="log_2_64bit" moduleName="KWTA_mini8_theta" rtlName="tmp5_fu_1341_p2" latency="0" BRAM="-1" DSP="-1" FF="0" LUT="15" fileDirectory="/home/tingyuan/Temporary/vivado-outputs"><\/item>
<item  id="446" filename="KWTAmini8_0/top.cc" linenumber="95" name="tmp5_cast" contextFuncName="log_2_64bit" moduleName="KWTA_mini8_theta" rtlName="tmp5_cast_fu_1347_p1" latency="0" BRAM="-1" DSP="-1" FF="-1" LUT="-1" fileDirectory="/home/tingyuan/Temporary/vivado-outputs"><\/item>
<item  id="447" filename="KWTAmini8_0/top.cc" linenumber="95" name="tmp6" contextFuncName="log_2_64bit" moduleName="KWTA_mini8_theta" rtlName="tmp6_fu_1351_p2" latency="0" BRAM="-1" DSP="-1" FF="0" LUT="15" fileDirectory="/home/tingyuan/Temporary/vivado-outputs"><\/item>
<item  id="448" filename="KWTAmini8_0/top.cc" linenumber="95" name="tmp6_cast" contextFuncName="log_2_64bit" moduleName="KWTA_mini8_theta" rtlName="tmp6_cast_fu_1357_p1" latency="0" BRAM="-1" DSP="-1" FF="-1" LUT="-1" fileDirectory="/home/tingyuan/Temporary/vivado-outputs"><\/item>
<item  id="449" filename="KWTAmini8_0/top.cc" linenumber="95" name="loc2_V" contextFuncName="log_2_64bit" moduleName="KWTA_mini8_theta" rtlName="loc2_V_fu_1361_p2" latency="0" BRAM="-1" DSP="-1" FF="0" LUT="15" fileDirectory="/home/tingyuan/Temporary/vivado-outputs"><\/item>
<item  id="451" filename="KWTAmini8_0/top.cc" linenumber="156" name="r_V" contextFuncName="KWTA_mini8_theta" moduleName="KWTA_mini8_theta" rtlName="r_V_fu_1373_p2" latency="0" BRAM="-1" DSP="-1" FF="-1" LUT="-1" fileDirectory="/home/tingyuan/Temporary/vivado-outputs"><\/item>
<item  id="452" filename="KWTAmini8_0/top.cc" linenumber="156" name="lhs_V" contextFuncName="KWTA_mini8_theta" moduleName="KWTA_mini8_theta" rtlName="lhs_V_fu_1378_p1" latency="0" BRAM="-1" DSP="-1" FF="-1" LUT="-1" fileDirectory="/home/tingyuan/Temporary/vivado-outputs"><\/item>
<item  id="453" filename="KWTAmini8_0/top.cc" linenumber="156" name="rhs_V" contextFuncName="KWTA_mini8_theta" moduleName="KWTA_mini8_theta" rtlName="rhs_V_fu_1382_p1" latency="0" BRAM="-1" DSP="-1" FF="-1" LUT="-1" fileDirectory="/home/tingyuan/Temporary/vivado-outputs"><\/item>
<item  id="454" filename="KWTAmini8_0/top.cc" linenumber="156" name="r_V_1" contextFuncName="KWTA_mini8_theta" moduleName="KWTA_mini8_theta" rtlName="r_V_1_fu_1385_p2" latency="0" BRAM="-1" DSP="-1" FF="0" LUT="15" fileDirectory="/home/tingyuan/Temporary/vivado-outputs"><\/item>
<item  id="455" filename="KWTAmini8_0/top.cc" linenumber="156" name="tmp_27" contextFuncName="KWTA_mini8_theta" moduleName="KWTA_mini8_theta" rtlName="tmp_27_fu_1396_p1" latency="0" BRAM="-1" DSP="-1" FF="-1" LUT="-1" fileDirectory="/home/tingyuan/Temporary/vivado-outputs"><\/item>
<item  id="457" filename="KWTAmini8_0/top.cc" linenumber="157" name="tmp_28" contextFuncName="KWTA_mini8_theta" moduleName="KWTA_mini8_theta" rtlName="tmp_28_fu_1391_p1" latency="0" BRAM="-1" DSP="-1" FF="-1" LUT="-1" fileDirectory="/home/tingyuan/Temporary/vivado-outputs"><\/item>
<item  id="460" filename="KWTAmini8_0/top.cc" linenumber="157" name="p_Result_8" contextFuncName="KWTA_mini8_theta" moduleName="KWTA_mini8_theta" rtlName="p_Result_8_fu_1405_p5" latency="0" BRAM="-1" DSP="-1" FF="-1" LUT="-1" fileDirectory="/home/tingyuan/Temporary/vivado-outputs"><\/item>
<item  id="463" filename="KWTAmini8_0/top.cc" linenumber="158" name="tmp_29" contextFuncName="KWTA_mini8_theta" moduleName="KWTA_mini8_theta" rtlName="tmp_29_fu_1418_p3" latency="0" BRAM="-1" DSP="-1" FF="-1" LUT="-1" fileDirectory="/home/tingyuan/Temporary/vivado-outputs"><\/item>
<item  id="464" filename="KWTAmini8_0/top.cc" linenumber="158" name="phitmp" contextFuncName="KWTA_mini8_theta" moduleName="KWTA_mini8_theta" rtlName="phitmp_fu_1425_p2" latency="0" BRAM="-1" DSP="-1" FF="0" LUT="12" fileDirectory="/home/tingyuan/Temporary/vivado-outputs"><\/item>
<item  id="465" filename="KWTAmini8_0/top.cc" linenumber="158" name="phitmp_cast" contextFuncName="KWTA_mini8_theta" moduleName="KWTA_mini8_theta" rtlName="phitmp_cast_fu_1431_p1" latency="0" BRAM="-1" DSP="-1" FF="-1" LUT="-1" fileDirectory="/home/tingyuan/Temporary/vivado-outputs"><\/item>
<item  id="469" filename="KWTAmini8_0/top.cc" linenumber="161" name="tmp_35_cast" contextFuncName="KWTA_mini8_theta" moduleName="KWTA_mini8_theta" rtlName="tmp_35_cast_fu_1441_p1" latency="0" BRAM="-1" DSP="-1" FF="-1" LUT="-1" fileDirectory="/home/tingyuan/Temporary/vivado-outputs"><\/item>
<item  id="470" filename="KWTAmini8_0/top.cc" linenumber="161" name="tmp_31" contextFuncName="KWTA_mini8_theta" moduleName="KWTA_mini8_theta" rtlName="tmp_31_fu_1444_p2" latency="0" BRAM="-1" DSP="-1" FF="0" LUT="17" fileDirectory="/home/tingyuan/Temporary/vivado-outputs"><\/item>
<item  id="471" filename="KWTAmini8_0/top.cc" linenumber="161" name="tmp_36_cast" contextFuncName="KWTA_mini8_theta" moduleName="KWTA_mini8_theta" rtlName="tmp_36_cast_fu_1450_p1" latency="0" BRAM="-1" DSP="-1" FF="-1" LUT="-1" fileDirectory="/home/tingyuan/Temporary/vivado-outputs"><\/item>
</annotationInfo>
